aptc/__init__.py
aptc/configs.py
aptc/libs/__init__.py
aptc/libs/_types.py
aptc/libs/apis.py
aptc/libs/client.py
aptc/libs/const.py
aptc/libs/errors.py
aptc/libs/utils.py
aptc/libs/providers/__init__.py
aptc/libs/providers/_base.py
aptc/libs/providers/async_http.py
aptc/libs/providers/http.py
aptc/sdk_impl/__init__.py
aptc/sdk_impl/account.py
aptc/sdk_impl/account_address.py
aptc/sdk_impl/bcs.py
aptc/sdk_impl/ed25519.py
aptc-0.0.3.dist-info/LICENSE
aptc-0.0.3.dist-info/METADATA
aptc-0.0.3.dist-info/WHEEL
aptc-0.0.3.dist-info/top_level.txt
aptc-0.0.3.dist-info/RECORD
