Metadata-Version: 2.1
Name: aptc
Version: 0.0.3
Summary: A simple web3py like client for APTOS chain.
Home-page: https://github.com/ackness/aptc
Author: Yong
Author-email: ackness8@gmail.com
License: MIT
Keywords: apt,aptos,block chain,web3
Requires-Python: >=3.7
License-File: LICENSE
Requires-Dist: httpx
Requires-Dist: PyNaCl
